4to1mux/design.sv
// Code your design here
module mux2to1(w0,w1,s,f);
  
  input w0,w1,s;
  output reg f;
  
  always@(*)
    if (s==0)
      f=w0;
  	else
      f=w1;
  
  
endmodule

module mux4to1(w,s,f);
  
  input [3:0]w;
  input [1:0]s;
  output f;
  wire [1:0]c;
  
  mux2to1 x1 (w[0],w[1],s[0],c[0]);
  
  mux2to1 x2 (w[2],w[3],s[0],c[1]);
    
  mux2to1 x3 (c[0],c[1],s[1],f);
  
  
endmodule

4to1mux/testbench.sv
// Code your testbench here
// or browse Examples
module tb;
  reg [3:0]w;
  reg [1:0]s;
  output f;
 
  mux4to1 tb(w,s,f);
  
  initial
    begin
      w=4'bxxxx;
      s=0;
      
      repeat(20)
        begin
          #5;
          w=$random;
          s=$random;
        end
    end
  
  initial
    begin
      $monitor($time, " W: %b S: %b f:%b", w,s,f);
      $dumpfile("dump.vcd");
      $dumpvars(1);
    end
  
endmodule

4to1mux/dump.vcd
$date
	Wed Aug 12 02:50:47 2020
$end
$version
	Icarus Verilog
$end
$timescale
	1s
$end
$scope module tb $end
$var wire 1 ! f $end
$var reg 2 " s [1:0] $end
$var reg 4 # w [3:0] $end
$upscope $end
$enddefinitions $end
#0
$dumpvars
bx #
b0 "
x!
$end
#5
0!
b1 "
b100 #
#10
1!
b11 "
b1001 #
#15
0!
b1 "
b1101 #
#20
1!
b10 "
b101 #
#25
0!
b1 "
b1 #
#30
1!
b110 #
#35
b0 "
b1101 #
#40
0!
b10 "
b1001 #
#45
1!
b101 #
#50
0!
b11 "
#55
b10 #
#60
b10 "
#65
b1 "
b1000 #
#70
b1100 #
#75
b1101 #
#80
0!
b10 "
b11 #
#85
0!
b0 "
b0 #
#90
1!
b1 "
b1010 #
#95
0!
b11 "
b110 #
#100
1!
b1101 #
