Seq_detector/design.sv
// Code your design here
module seq_detector(clk, d, reset, Z); //0101 overlapping Moore
  
  input clk;
  input d;
  input reset;
  output reg Z;
  reg [2:0] y, Y;//states
  parameter SI =3'b000, S0=3'b001, S01=3'b010, S010=3'b011, S0101=3'b100;
  
  //combinational block
  
  always@(d,y)
      begin 
      case(y)
        SI: if (d==0)
              begin
                  Y=S0;
                  Z=0;
              end	
              else
              begin
                  Y=SI;
                  Z=0;
              end
        
        S0: if (d==0)
              begin
                  Y=S0;
                  Z=0;
              end	
              else
              begin
                  Y=S01;
                  Z=0;
              end
                
        S01: if (d==0)
              begin
                  Y=S010;
                  Z=0;
              end	
              else
              begin
                  Y=SI;
                  Z=0;
              end

        S010: if (d==0)
              begin
                  Y=S0;
                  Z=0;
              end	
              else
              begin
                  Y=S0101;
                  Z=0;
              end
        S0101: if (d==0)
              begin
                  Y=S010;
                  Z=1;
              end	
              else
              begin
                  Y=SI;
                  Z=1;
              end
        default:
          	begin
              Z=1'bz;
              Y=SI;
            end
      endcase
    end
  
      
      
      //seq block
      
  always@(posedge clk)
        y=Y;
  
  always@(negedge reset)
        y=SI;
      
endmodule

Seq_detector/testbench.sv
// Code your testbench here
// or browse Examples
`timescale 100ps/1ps
module testbench;
  reg clk,d,reset;
  wire Z;
  
  seq_detector x1(clk,d,reset,Z);
  
  always #5 clk=~clk;
  
  initial
    begin
      clk=0;
      reset=1;
      #5 reset =0;
      #10 d=1;
      #10 d=0;
      #10 d=1;
      #10 d=0;
      #10 d=1;
   	  #10 reset =0;
      #10 reset =1;
      #10 d=1;
      #10 d=0;
      #10 d=1;
      #10 d=0;
      #10 d=1;
    end
  
  initial
    begin
      $dumpfile("dump.vcd");
      $dumpvars(1);
      $monitor ($time, "d: %b  Z: %b reset: %b",d,Z,reset);
      #150 $finish;
    end
  
endmodule

Seq_detector/dump.vcd
$date
	Sun Oct  4 08:52:30 2020
$end
$version
	Icarus Verilog
$end
$timescale
	1ps
$end
$scope module testbench $end
$var wire 1 ! Z $end
$var reg 1 " clk $end
$var reg 1 # d $end
$var reg 1 $ reset $end
$upscope $end
$enddefinitions $end
#0
$dumpvars
1$
x#
0"
x!
$end
#500
0!
0$
1"
#1000
0"
#1500
1"
1#
#2000
0"
#2500
1"
0#
#3000
0"
#3500
1"
1#
#4000
0"
#4500
1"
0#
#5000
0"
#5500
1!
1"
1#
#6000
0"
#6500
0!
1"
#7000
0"
#7500
1"
1$
#8000
0"
#8500
1"
#9000
0"
#9500
1"
0#
#10000
0"
#10500
1"
1#
#11000
0"
#11500
1"
0#
#12000
0"
#12500
1!
1"
1#
#13000
0"
#13500
0!
1"
