D_ff/design.sv
// Code your design here
module D_ff (D,Q,reset,clk);
  input D;
  input clk;
  input reset;
  output reg Q;
 
  always @(posedge clk,reset)
    begin
    	if(reset==0)
          Q<= 0;
      	else
          Q<=D;
    end
  
  
endmodule

D_ff/testbench.sv
// Code your testbench here
// or browse Examples

module tb;
  
  reg D,reset,clk;
  output Q;
  
  //instantiate
  D_ff ex(D,Q,reset,clk); 
 
  always #5 clk= ~clk;
  
  initial
    clk =0;
  
  
   
  
  initial
    begin
      #2 D=0;
      reset=1;
  
      repeat(10)
        begin
          #5;
          D=$random;
          reset=$random;
         // $display($time , " D: %b Q: %b reset: %b clk:%b",D,Q,reset,clk);
        end
      
    end
  
 initial
   begin
     $dumpfile("dump.vcd");
     $dumpvars(1);
    $monitor($time , " D: %b Q: %b reset: %b clk:%b",D,Q,reset,clk);
  	# 50 $finish;
   end
  

         
  
endmodule

D_ff/dump.vcd
$date
	Wed Aug 12 02:10:18 2020
$end
$version
	Icarus Verilog
$end
$timescale
	1s
$end
$scope module tb $end
$var wire 1 ! Q $end
$var reg 1 " D $end
$var reg 1 # clk $end
$var reg 1 $ reset $end
$upscope $end
$enddefinitions $end
#0
$dumpvars
x$
0#
x"
x!
$end
#2
0!
1$
0"
#5
1#
#10
0#
#12
1"
#15
1!
1#
#20
0#
#22
0!
0$
#25
1#
#27
1!
1$
#30
0#
#32
0"
#35
0!
1#
#37
0$
1"
